flet_toast/__init__.py
flet_toast/Controls/__init__.py
flet_toast/Controls/controls.py
flet_toast/Toast/__init__.py
flet_toast/Toast/toast.py
flet_toast/Types/__init__.py
flet_toast/Types/types.py
flet_toast-0.6.0.dist-info/LICENCE
flet_toast-0.6.0.dist-info/METADATA
flet_toast-0.6.0.dist-info/WHEEL
flet_toast-0.6.0.dist-info/top_level.txt
flet_toast-0.6.0.dist-info/RECORD
