Metadata-Version: 2.1
Name: flet-toast
Version: 0.6.0
Summary: Cria interface para exibir notificações na tela
Home-page: https://github.com/webtechmoz/flet-toast.git
Author: Web Tech Moz
Author-email: zoidycine@gmail.com
License: MIT
Keywords: toastfy,toasty-flet,flet-toast,toast,flet
Classifier: Programming Language :: Python :: 3.10
Classifier: License :: OSI Approved :: MIT License
Classifier: Operating System :: OS Independent
Requires-Python: >=3.10
License-File: LICENCE
